odoo/addons/misc_settings/README.rst
odoo/addons/misc_settings/__init__.py
odoo/addons/misc_settings/__manifest__.py
odoo/addons/misc_settings/i18n/fr.po
odoo/addons/misc_settings/i18n/it.po
odoo/addons/misc_settings/i18n/misc_settings.pot
odoo/addons/misc_settings/readme/CONFIGURE.rst
odoo/addons/misc_settings/readme/CONTRIBUTORS.rst
odoo/addons/misc_settings/readme/DESCRIPTION.rst
odoo/addons/misc_settings/static/description/icon.png
odoo/addons/misc_settings/static/description/index.html
odoo/addons/misc_settings/static/description/screen.png
odoo/addons/misc_settings/views/res_config_settings.xml
odoo_addon_misc_settings-16.0.1.0.0.4.dist-info/METADATA
odoo_addon_misc_settings-16.0.1.0.0.4.dist-info/WHEEL
odoo_addon_misc_settings-16.0.1.0.0.4.dist-info/top_level.txt
odoo_addon_misc_settings-16.0.1.0.0.4.dist-info/RECORD
