Metadata-Version: 2.1
Name: odoo-addon-misc-settings
Version: 16.0.1.0.0.4
Summary: Miscellaneous settings to be an anchor for your custom settings
Home-page: https://github.com/OCA/server-ux
Author: Akretion,Odoo Community Association (OCA)
Author-email: support@odoo-community.org
License: AGPL-3
Platform: UNKNOWN
Classifier: Programming Language :: Python
Classifier: Framework :: Odoo
Classifier: Framework :: Odoo :: 16.0
Classifier: License :: OSI Approved :: GNU Affero General Public License v3
Requires-Python: >=3.10
Requires-Dist: odoo <16.1dev,>=16.0a
